dotcode/__init__.py
dotcode/common/__init__.py
dotcode/dot/__init__.py
dotcode/dot/cli.py
dotcode/dot/compiler.py
dotcode/dot/runtime.py
dotcode/numdot/__init__.py
dotcode/numdot/cli.py
dotcode/numdot/compiler.py
dotcode/numdot/runtime.py
dotcode-1.0.1.dist-info/licenses/LICENSE.txt
dotcode-1.0.1.dist-info/METADATA
dotcode-1.0.1.dist-info/WHEEL
dotcode-1.0.1.dist-info/entry_points.txt
dotcode-1.0.1.dist-info/top_level.txt
dotcode-1.0.1.dist-info/RECORD
