Metadata-Version: 2.4
Name: dotcode
Version: 1.0.1
Summary: DotCode: Dot and NumDot esoteric programming languages
Author-email: Edwin Sam K Reju <projectcarbonit@gmail.com>
License: MIT
Project-URL: Homepage, https://github.com/CarbonIt-Labs/dotcode
Project-URL: Repository, https://github.com/CarbonIt-Labs/dotcode
Requires-Python: >=3.8
License-File: LICENSE.txt
Dynamic: license-file
